ultraprint/__init__.py
ultraprint/common.py
ultraprint/logging.py
ultraprint-3.5.0.dist-info/licenses/LICENSE.rst
ultraprint-3.5.0.dist-info/METADATA
ultraprint-3.5.0.dist-info/WHEEL
ultraprint-3.5.0.dist-info/top_level.txt
ultraprint-3.5.0.dist-info/RECORD
