Metadata-Version: 2.4
Name: ultraprint
Version: 3.5.0
Summary: Ultraprint is a versatile Python library that enhances your command-line output with colorful text, styled formatting, and easy-to-use logging utilities. Perfect for creating visually appealing console applications.
Home-page: https://github.com/Kawai-Senpai/UltraPrint
Download-URL: https://github.com/Kawai-Senpai/UltraPrint
Author: Ranit Bhowmick
Author-email: bhowmickranitking@duck.com
License: MIT License with attribution requirement
Keywords: Printing,Console,Formatting,Logging,Colored Output,Styled Text
License-File: LICENSE.rst
Dynamic: author
Dynamic: author-email
Dynamic: description
Dynamic: description-content-type
Dynamic: download-url
Dynamic: home-page
Dynamic: keywords
Dynamic: license
Dynamic: license-file
Dynamic: summary
